tlru/__init__.py
tlru/version.py
tlru-0.3.1.dist-info/LICENSE
tlru-0.3.1.dist-info/METADATA
tlru-0.3.1.dist-info/WHEEL
tlru-0.3.1.dist-info/top_level.txt
tlru-0.3.1.dist-info/RECORD
