Metadata-Version: 2.1
Name: tlru
Version: 0.3.1
Summary: Time-bound LRU caching library
Home-page: https://github.com/falconry/tlru
Author: Kurt Griffiths
Author-email: mail@kgriffs.com
License: UNKNOWN
Platform: UNKNOWN
Classifier: Development Status :: 3 - Alpha
Classifier: Natural Language :: English
Classifier: Intended Audience :: Developers
Classifier: License :: OSI Approved :: Apache Software License
Classifier: Operating System :: MacOS :: MacOS X
Classifier: Operating System :: Microsoft :: Windows
Classifier: Operating System :: POSIX
Classifier: Topic :: Software Development :: Libraries
Classifier: Programming Language :: Python
Classifier: Programming Language :: Python :: Implementation :: CPython
Classifier: Programming Language :: Python :: Implementation :: PyPy
Classifier: Programming Language :: Python :: 3
Classifier: Programming Language :: Python :: 3.6
Classifier: Programming Language :: Python :: 3.7
Classifier: Programming Language :: Python :: 3.8
Requires-Python: >=3.6.2
License-File: LICENSE
Requires-Dist: backoff
Requires-Dist: csiphash
Requires-Dist: msgpack
Requires-Dist: pecyn
Requires-Dist: xxhash
